MANIFEST.in
README.txt
fileslice.py
setup.py
docs/source/index.rst
docs/source/installation.rst
docs/source/quick-guide.rst
docs/source/reference.rst
fileslice.egg-info/PKG-INFO
fileslice.egg-info/SOURCES.txt
fileslice.egg-info/dependency_links.txt
fileslice.egg-info/top_level.txt