Metadata-Version: 1.1
Name: fileslice
Version: 0.0.1
Summary: File slice is a part of a file. This library allows you to open a binary file and see only part of it.
Home-page: https://github.com/alghafli/fileslice
Author: Mohammad Alghafli
Author-email: thebsom@gmail.com
License: UNKNOWN
Keywords: file,slice,region,part
Platform: UNKNOWN
Classifier: Development Status :: 4 - Beta
Classifier: Intended Audience :: Developers
Classifier: License :: OSI Approved :: GNU General Public License v3 (GPLv3)
Classifier: Programming Language :: Python :: 3.1
